Metadata-Version: 2.1
Name: NeuralPlayground
Version: 0.0.9
Summary: The standardised environment for the hippocampus and entorhinal cortex models
Author: Clementine Domine
Author-email: Rodrigo Carrasco-Davis <rodrigo.carrasco.davis@gmail.com>
License: MIT
Project-URL: Homepage, https://github.com/ClementineDomine/NeuralPlayground
Project-URL: Bug tracker, https://github.com/ClementineDomine/NeuralPlayground/issues
Project-URL: Documentation, https://github.com/ClementineDomine/NeuralPlayground
Project-URL: Source code, https://github.com/ClementineDomine/NeuralPlayground
Project-URL: User support, https://github.com/ClementineDomine/NeuralPlayground/issues
Classifier: Development Status :: 3 - Alpha
Classifier: Programming Language :: Python
Classifier: Programming Language :: Python :: 3
Classifier: Programming Language :: Python :: 3.8
Classifier: Programming Language :: Python :: 3.9
Classifier: Programming Language :: Python :: 3.10
Classifier: Programming Language :: Python :: 3.11
Classifier: Operating System :: OS Independent
Classifier: License :: OSI Approved :: MIT License
Requires-Python: >=3.8.0
License-File: LICENSE
Requires-Dist: scipy
Requires-Dist: pandas
Requires-Dist: tqdm
Requires-Dist: jupyter
Requires-Dist: ipython
Requires-Dist: matplotlib
Requires-Dist: deepdiff
Requires-Dist: opencv-python
Requires-Dist: gymnasium
Requires-Dist: scikit-image
Requires-Dist: pooch
Requires-Dist: colorama
Provides-Extra: dev
Requires-Dist: pytest; extra == "dev"
Requires-Dist: pytest-cov; extra == "dev"
Requires-Dist: coverage; extra == "dev"
Requires-Dist: tox; extra == "dev"
Requires-Dist: black; extra == "dev"
Requires-Dist: mypy; extra == "dev"
Requires-Dist: pre-commit; extra == "dev"
Requires-Dist: ruff; extra == "dev"
Requires-Dist: setuptools-scm; extra == "dev"
Requires-Dist: torch; extra == "dev"
Requires-Dist: tensorboard; extra == "dev"
